setup.py
socketproxy/__init__.py
socketproxy.egg-info/PKG-INFO
socketproxy.egg-info/SOURCES.txt
socketproxy.egg-info/dependency_links.txt
socketproxy.egg-info/entry_points.txt
socketproxy.egg-info/top_level.txt