Metadata-Version: 1.0
Name: socketproxy
Version: 0.1
Summary: Proxy TCP connections with stream manipulation
Home-page: http://github.com/nijotz/socketproxy
Author: Nick Tzaperas
Author-email: nick@nijotz.com
License: UNKNOWN
Platform: UNKNOWN
